mstache/__init__.py
mstache/py.typed
mstache-0.3.0.dist-info/LICENSE
mstache-0.3.0.dist-info/METADATA
mstache-0.3.0.dist-info/WHEEL
mstache-0.3.0.dist-info/entry_points.txt
mstache-0.3.0.dist-info/top_level.txt
mstache-0.3.0.dist-info/zip-safe
mstache-0.3.0.dist-info/RECORD
