Metadata-Version: 2.1
Name: mstache
Version: 0.3.0
Summary: mstache, Mustache for Python
Home-page: https://gitlab.com/ergoithz/mstache
Author: Felipe A Hernandez
Author-email: ergoithz@gmail.com
License: MIT
Keywords: template,mustache
Platform: any
Classifier: License :: OSI Approved :: MIT License
Classifier: Development Status :: 4 - Beta
Classifier: Operating System :: OS Independent
Classifier: Programming Language :: Python :: 3
Classifier: Programming Language :: Python :: 3.10
Classifier: Topic :: Software Development :: Libraries
Requires-Python: >=3.10.0
License-File: LICENSE
Provides-Extra: benchmark
Requires-Dist: chevron ; extra == 'benchmark'
Requires-Dist: tabulate ; extra == 'benchmark'
Provides-Extra: codestyle
Requires-Dist: pycodestyle ; extra == 'codestyle'
Requires-Dist: ruff ; extra == 'codestyle'
Requires-Dist: sphinx ; extra == 'codestyle'
Requires-Dist: rstcheck ; extra == 'codestyle'
Requires-Dist: mypy ; extra == 'codestyle'
Provides-Extra: coverage
Requires-Dist: coverage[toml] ; extra == 'coverage'
Provides-Extra: dev
Requires-Dist: pycodestyle ; extra == 'dev'
Requires-Dist: ruff ; extra == 'dev'
Requires-Dist: sphinx ; extra == 'dev'
Requires-Dist: rstcheck ; extra == 'dev'
Requires-Dist: mypy ; extra == 'dev'
Requires-Dist: coverage[toml] ; extra == 'dev'
Requires-Dist: myst-parser ; extra == 'dev'
Requires-Dist: sphinx-autobuild ; extra == 'dev'
Requires-Dist: sphinx-autodoc-typehints ; extra == 'dev'
Requires-Dist: build ; extra == 'dev'
Requires-Dist: twine ; extra == 'dev'
Requires-Dist: chevron ; extra == 'dev'
Requires-Dist: tabulate ; extra == 'dev'
Provides-Extra: docs
Requires-Dist: myst-parser ; extra == 'docs'
Requires-Dist: sphinx ; extra == 'docs'
Requires-Dist: sphinx-autobuild ; extra == 'docs'
Requires-Dist: sphinx-autodoc-typehints ; extra == 'docs'
Provides-Extra: release
Requires-Dist: build ; extra == 'release'
Requires-Dist: twine ; extra == 'release'
